{"parsed":{"_path":"/comics/capitolo-13","_dir":"comics","_draft":false,"_partial":false,"_locale":"","title":"13: Las Alcantarillas de la Resistencia","description":"En el subsuelo, la Matriarca Cebolla espera. Para obtener el último sello, Patato debe llorar y romper su coraza emocional. La Armonía final.","cover":"../capitoli/capitulo13/VCover.mp4","releaseDate":"2027-04-21","audioTheme":"../audio/TKILTRAILERHYPE.mp3","panels":[{"type":"Video","src":"../capitoli/capitulo2/V01.mp4","textOverlay":"","textEffect":""},{"type":"Video","src":"../capitoli/capitulo2/V02.mp4","textOverlay":"","textEffect":""}],"_id":"content:comics:capitolo-13.json","_type":"json","_source":"content","_file":"comics/capitolo-13.json","_stem":"comics/capitolo-13","_extension":"json"},"hash":"fiONpj8Jlf"}